alas_ce0_whatsapp-0.5.data/data/yowsup/common/mime.types
alas_ce0_whatsapp-0.5.data/scripts/yowsup-cli
alas_ce0_whatsapp-0.5.dist-info/DESCRIPTION.rst
alas_ce0_whatsapp-0.5.dist-info/METADATA
alas_ce0_whatsapp-0.5.dist-info/RECORD
alas_ce0_whatsapp-0.5.dist-info/WHEEL
alas_ce0_whatsapp-0.5.dist-info/metadata.json
alas_ce0_whatsapp-0.5.dist-info/top_level.txt
yowsup/__init__.py
yowsup/common/__init__.py
yowsup/common/constants.py
yowsup/common/mime.types
yowsup/common/optionalmodules.py
yowsup/common/tools.py
yowsup/common/http/__init__.py
yowsup/common/http/httpproxy.py
yowsup/common/http/test_warequest.py
yowsup/common/http/warequest.py
yowsup/common/http/waresponseparser.py
yowsup/demos/__init__.py
yowsup/demos/cli/__init__.py
yowsup/demos/cli/cli.py
yowsup/demos/cli/layer.py
yowsup/demos/cli/stack.py
yowsup/demos/contacts/__init__.py
yowsup/demos/contacts/layer.py
yowsup/demos/contacts/stack.py
yowsup/demos/echoclient/__init__.py
yowsup/demos/echoclient/layer.py
yowsup/demos/echoclient/stack.py
yowsup/demos/sendclient/__init__.py
yowsup/demos/sendclient/layer.py
yowsup/demos/sendclient/stack.py
yowsup/env/__init__.py
yowsup/env/env.py
yowsup/env/env_android.py
yowsup/env/env_s40.py
yowsup/env/test_env_s40.py
yowsup/layers/__init__.py
yowsup/layers/auth/__init__.py
yowsup/layers/auth/autherror.py
yowsup/layers/auth/keystream.py
yowsup/layers/auth/layer_authentication.py
yowsup/layers/auth/layer_crypt.py
yowsup/layers/auth/layer_interface_authentication.py
yowsup/layers/auth/test_authenticator.py
yowsup/layers/auth/test_crypt.py
yowsup/layers/auth/test_keystream.py
yowsup/layers/auth/protocolentities/__init__.py
yowsup/layers/auth/protocolentities/auth.py
yowsup/layers/auth/protocolentities/challenge.py
yowsup/layers/auth/protocolentities/failure.py
yowsup/layers/auth/protocolentities/response.py
yowsup/layers/auth/protocolentities/stream_error.py
yowsup/layers/auth/protocolentities/stream_features.py
yowsup/layers/auth/protocolentities/success.py
yowsup/layers/auth/protocolentities/test_auth.py
yowsup/layers/auth/protocolentities/test_challenge.py
yowsup/layers/auth/protocolentities/test_failure.py
yowsup/layers/auth/protocolentities/test_response.py
