Metadata-Version: 2.0
Name: alas-ce0-whatsapp
Version: 0.5
Summary: A WhatsApp python library for ALAS-Ce0
Home-page: https://github.com/pypa/alas-ce0-whatsapp
Author: Adonis Cesar Legón Campo
Author-email: alegon@alasxpress.com
License: GPL-3+
Platform: any
Classifier: Programming Language :: Python
Classifier: Development Status :: 4 - Beta
Classifier: Natural Language :: English
Classifier: Intended Audience :: Developers
Classifier: License :: OSI Approved :: GNU General Public License v3 or later (GPLv3+)
Classifier: Operating System :: OS Independent
Classifier: Topic :: Software Development :: Libraries :: Python Modules
Requires-Dist: argparse
Requires-Dist: python-axolotl (>=0.1.39)
Requires-Dist: python-dateutil
Requires-Dist: six
